aitpi/__init__.py
aitpi/__main__.py
aitpi/command_library.py
aitpi/consumer.py
aitpi/folder_watch.py
aitpi/initializer.py
aitpi/input_converter.py
aitpi/input_initializer.py
aitpi/message.py
aitpi/mirrored_json.py
aitpi/pi_input_initializer.py
aitpi/postal_service.py
aitpi/printer.py
aitpi_c3n3-0.0.2.dist-info/LICENSE
aitpi_c3n3-0.0.2.dist-info/METADATA
aitpi_c3n3-0.0.2.dist-info/WHEEL
aitpi_c3n3-0.0.2.dist-info/top_level.txt
aitpi_c3n3-0.0.2.dist-info/RECORD
