Metadata-Version: 2.1
Name: aitpi-c3n3
Version: 0.0.2
Summary: A tool to setup arbitrary button configurations
Home-page: https://github.com/c3n3/AITPI
Author: Caden Churchman
Author-email: ccaden21@gmail.com
License: UNKNOWN
Project-URL: Bug Tracker, https://github.com/c3n3/AITPI/issues
Platform: UNKNOWN
Classifier: Programming Language :: Python :: 3
Classifier: License :: OSI Approved :: MIT License
Classifier: Operating System :: POSIX :: Linux
Requires-Python: >=3.6
License-File: LICENSE
